[
  {
    "bloodType": "A+",
    "status": "Moderate",
    "fillLevel": "66%"
  },
  {
    "bloodType": "B+",
    "status": "Moderate",
    "fillLevel": "54%"
  },
  {
    "bloodType": "O+",
    "status": "Moderate",
    "fillLevel": "60%"
  },
  {
    "bloodType": "AB+",
    "status": "Moderate",
    "fillLevel": "73%"
  },
  {
    "bloodType": "A-",
    "status": "Healthy",
    "fillLevel": "97%"
  },
  {
    "bloodType": "B-",
    "status": "Moderate",
    "fillLevel": "63%"
  },
  {
    "bloodType": "O-",
    "status": "Moderate",
    "fillLevel": "65%"
  },
  {
    "bloodType": "AB-",
    "status": "Low",
    "fillLevel": "33%"
  }
]